{"_notifyingListeners":false,"_scopeListeners":[],"_eventProcessors":[],"_breadcrumbs":[{"timestamp":1699397870.122,"category":"console","level":"log","message":"Discord 0.0.29"},{"timestamp":1699397870.33,"category":"electron","message":"app.will-finish-launching","type":"ui"},{"timestamp":1699397870.337,"category":"electron","message":"app.ready","type":"ui"},{"timestamp":1699397870.375,"category":"electron","message":"app.session-created","type":"ui"},{"timestamp":1699397870.375,"category":"console","level":"log","message":"Starting app."},{"timestamp":1699397870.378,"category":"console","level":"log","message":"Starting updater."},{"timestamp":1699397870.382,"category":"console","level":"log","message":"2023-11-07T22:57:50.379Z [Modules] Modules initializing"},{"timestamp":1699397870.382,"category":"console","level":"log","message":"2023-11-07T22:57:50.382Z [Modules] Distribution: remote"},{"timestamp":1699397870.382,"category":"console","level":"log","message":"2023-11-07T22:57:50.382Z [Modules] Host updates: enabled"},{"timestamp":1699397870.383,"category":"console","level":"log","message":"2023-11-07T22:57:50.383Z [Modules] Module updates: enabled"},{"timestamp":1699397870.383,"category":"console","level":"log","message":"2023-11-07T22:57:50.383Z [Modules] Module install path: /home/owl/.config/discord/0.0.29/modules"},{"timestamp":1699397870.383,"category":"console","level":"log","message":"2023-11-07T22:57:50.383Z [Modules] Module installed file path: /home/owl/.config/discord/0.0.29/modules/installed.json"},{"timestamp":1699397870.383,"category":"console","level":"log","message":"2023-11-07T22:57:50.383Z [Modules] Module download path: /home/owl/.config/discord/0.0.29/modules/pending"},{"timestamp":1699397870.385,"category":"console","level":"log","message":"splashScreen.initSplash(false)"},{"timestamp":1699397870.436,"category":"electron","message":"app.web-contents-created","type":"ui"},{"timestamp":1699397870.438,"category":"electron","message":"app.browser-window-created","type":"ui"},{"timestamp":1699397870.448,"category":"electron","message":"renderer.load-url","type":"ui","data":{}},{"timestamp":1699397870.463,"category":"electron","message":"app.gpu-info-update","type":"ui"},{"timestamp":1699397870.662,"category":"console","level":"log","message":"splashScreen: SPLASH_SCREEN_READY"},{"timestamp":1699397870.665,"category":"console","level":"log","message":"splashScreen.webContentsSend: SPLASH_SCREEN_QUOTE SPLASH_SCREEN_QUOTE [ 'Hold Tight — Loading Discord' ]"},{"timestamp":1699397870.678,"category":"electron","message":"window.show","type":"ui","data":{"id":1,"url":"app:///app_bootstrap/splash/index.html"}},{"timestamp":1699397870.679,"category":"console","level":"log","message":"2023-11-07T22:57:50.679Z [Modules] No updates to install"},{"timestamp":1699397870.68,"category":"console","level":"log","message":"splashScreen: no-pending-updates"},{"timestamp":1699397870.68,"category":"console","level":"log","message":"2023-11-07T22:57:50.680Z [Modules] Checking for host updates."},{"timestamp":1699397870.681,"category":"console","level":"log","message":"splashScreen: checking-for-updates"},{"timestamp":1699397870.681,"category":"console","level":"log","message":"splashScreen.updateSplashState checking-for-updates checking-for-updates {}"},{"timestamp":1699397870.682,"category":"console","level":"log","message":"splashScreen.webContentsSend: SPLASH_UPDATE_STATE SPLASH_UPDATE_STATE [ { status: 'checking-for-updates' } ]"},{"timestamp":1699397870.687,"category":"electron","message":"renderer.dom-ready","type":"ui","data":{"id":1,"url":"app:///app_bootstrap/splash/index.html"}},{"timestamp":1699397870.689,"category":"electron","message":"window.focus","type":"ui","data":{"id":1,"url":"app:///app_bootstrap/splash/index.html"}},{"timestamp":1699397870.689,"category":"electron","message":"app.browser-window-focus","type":"ui"},{"timestamp":1699397870.69,"category":"electron","message":"window.blur","type":"ui","data":{"id":1,"url":"app:///app_bootstrap/splash/index.html"}},{"timestamp":1699397870.69,"category":"electron","message":"app.browser-window-blur","type":"ui"},{"timestamp":1699397870.69,"category":"electron","message":"window.focus","type":"ui","data":{"id":1,"url":"app:///app_bootstrap/splash/index.html"}},{"timestamp":1699397870.69,"category":"electron","message":"app.browser-window-focus","type":"ui"}],"_attachments":[],"_user":{},"_tags":{},"_extra":{},"_contexts":{},"_sdkProcessingMetadata":{}}