{"version":1,"resource":"file:///home/owl/vyda/manage.sh","entries":[{"id":"M0SF.sh","timestamp":1694295547000},{"id":"bexZ.sh","timestamp":1694297003000},{"id":"3PYQ.sh","timestamp":1694297097000},{"id":"wPjt.sh","timestamp":1694299966000},{"id":"3HW9.sh","timestamp":1694299998000},{"id":"Urvr.sh","timestamp":1694300254000},{"id":"jDQY.sh","timestamp":1694300270000},{"id":"LJuD.sh","timestamp":1694300642000},{"id":"Fb5p.sh","timestamp":1694300668000},{"id":"pavJ.sh","timestamp":1694300758000},{"id":"myKv.sh","timestamp":1694300820000},{"id":"n47K.sh","timestamp":1694838898000},{"id":"iuat.sh","timestamp":1694838933000},{"id":"js7T.sh","timestamp":1694838978000},{"id":"99Cx.sh","timestamp":1694921325000},{"id":"EJZH.sh","timestamp":1694930372000},{"id":"5vRV.sh","timestamp":1694930384000}]}