{"version":1,"resource":"file:///home/owl/vyda/nginx.sh","entries":[{"id":"2JQ5.sh","timestamp":1694300659000},{"id":"OOni.sh","timestamp":1694300691000},{"id":"5Jt6.sh","timestamp":1694300729000},{"id":"r5AR.sh","timestamp":1694300862000},{"id":"Ncsv.sh","timestamp":1694408261000},{"id":"zlpa.sh","timestamp":1694408339000},{"id":"Xg59.sh","timestamp":1694408430000},{"id":"eAxv.sh","timestamp":1694499220000},{"id":"oc0G.sh","timestamp":1694499644000},{"id":"YiV8.sh","timestamp":1694828301000},{"id":"Pwtk.sh","timestamp":1694828345000},{"id":"y03Z.sh","timestamp":1694828356000},{"id":"wfTH.sh","timestamp":1694921404000},{"id":"3jLX.sh","timestamp":1694921435000},{"id":"sRzN.sh","timestamp":1694925400000},{"id":"Hyl6.sh","timestamp":1694930051000},{"id":"wPxN.sh","timestamp":1694973592000},{"id":"K35A.sh","timestamp":1694973619000},{"id":"H0Kd.sh","timestamp":1694975061000},{"id":"tmJ6.sh","timestamp":1694975096000},{"id":"qcKe.sh","timestamp":1694975849000},{"id":"kasY.sh","timestamp":1694976470000},{"id":"6BAE.sh","timestamp":1694976484000},{"id":"XiKr.sh","timestamp":1694976562000},{"id":"sQ0R.sh","timestamp":1696381786000},{"id":"VJ95.sh","timestamp":1696381956000},{"id":"0eyH.sh","timestamp":1696382013000},{"id":"2nxY.sh","timestamp":1696382025000},{"id":"ZGoE.sh","timestamp":1696382041000},{"id":"FjhQ.sh","timestamp":1696382066000},{"id":"cUyj.sh","timestamp":1696382086000},{"id":"uXPb.sh","timestamp":1696382210000},{"id":"dViJ.sh","timestamp":1696382225000},{"id":"bsrX.sh","timestamp":1696382298000},{"id":"H5yp.sh","timestamp":1696476737000},{"id":"zF5F.sh","timestamp":1696477849000},{"id":"hVgJ.sh","timestamp":1696477867000},{"id":"WVte.sh","timestamp":1696478129000},{"id":"9zJb.sh","timestamp":1697188361000}]}